{
  "version": "5.8.1",
  "flags": {},
  "shapes": [
    {
      "label": "DAMAGED_SIGN",
      "points": [
        [
          303.0,
          479.5
        ],
        [
          292.0,
          474.5
        ],
        [
          288.5,
          476.0
        ],
        [
          282.5,
          462.0
        ],
        [
          281.5,
          449.0
        ],
        [
          273.5,
          446.0
        ],
        [
          270.5,
          427.0
        ],
        [
          259.0,
          427.5
        ],
        [
          245.5,
          409.0
        ],
        [
          241.5,
          396.0
        ],
        [
          234.0,
          395.5
        ],
        [
          228.5,
          389.0
        ],
        [
          228.5,
          378.0
        ],
        [
          222.5,
          372.0
        ],
        [
          214.5,
          338.0
        ],
        [
          214.5,
          316.0
        ],
        [
          217.5,
          301.0
        ],
        [
          221.5,
          297.0
        ],
        [
          213.5,
          293.0
        ],
        [
          211.5,
          280.0
        ],
        [
          221.5,
          257.0
        ],
        [
          230.5,
          249.0
        ],
        [
          242.5,
          217.0
        ],
        [
          246.5,
          215.0
        ],
        [
          247.5,
          198.0
        ],
        [
          253.5,
          177.0
        ],
        [
          267.5,
          150.0
        ],
        [
          265.5,
          127.0
        ],
        [
          272.5,
          115.0
        ],
        [
          269.5,
          100.0
        ],
        [
          261.0,
          92.5
        ],
        [
          249.0,
          95.5
        ],
        [
          242.0,
          85.5
        ],
        [
          234.0,
          87.5
        ],
        [
          228.0,
          80.5
        ],
        [
          216.0,
          81.5
        ],
        [
          212.0,
          78.5
        ],
        [
          209.0,
          82.5
        ],
        [
          188.0,
          88.5
        ],
        [
          182.0,
          83.5
        ],
        [
          179.5,
          92.0
        ],
        [
          173.0,
          97.5
        ],
        [
          160.5,
          101.0
        ],
        [
          161.5,
          114.0
        ],
        [
          169.5,
          128.0
        ],
        [
          174.5,
          146.0
        ],
        [
          172.5,
          160.0
        ],
        [
          168.5,
          164.0
        ],
        [
          165.5,
          204.0
        ],
        [
          158.5,
          219.0
        ],
        [
          146.5,
          230.0
        ],
        [
          144.5,
          249.0
        ],
        [
          136.0,
          252.5
        ],
        [
          129.0,
          260.5
        ],
        [
          122.0,
          251.5
        ],
        [
          117.0,
          253.5
        ],
        [
          115.5,
          271.0
        ],
        [
          104.0,
          279.5
        ],
        [
          100.5,
          279.0
        ],
        [
          95.5,
          267.0
        ],
        [
          77.0,
          244.5
        ],
        [
          61.0,
          236.5
        ],
        [
          51.5,
          227.0
        ],
        [
          42.5,
          210.0
        ],
        [
          44.5,
          171.0
        ],
        [
          61.5,
          132.0
        ],
        [
          91.5,
          82.0
        ],
        [
          116.5,
          51.0
        ],
        [
          154.0,
          14.5
        ],
        [
          430.0,
          13.5
        ],
        [
          463.5,
          48.0
        ],
        [
          493.5,
          86.0
        ],
        [
          526.5,
          141.0
        ],
        [
          536.5,
          169.0
        ],
        [
          553.5,
          238.0
        ],
        [
          561.5,
          303.0
        ],
        [
          562.5,
          409.0
        ],
        [
          552.5,
          465.0
        ],
        [
          544.0,
          472.5
        ],
        [
          544.5,
          469.0
        ],
        [
          535.0,
          456.5
        ],
        [
          519.5,
          452.0
        ],
        [
          515.5,
          430.0
        ],
        [
          500.5,
          420.0
        ],
        [
          499.5,
          405.0
        ],
        [
          492.0,
          404.5
        ],
        [
          482.5,
          392.0
        ],
        [
          478.5,
          383.0
        ],
        [
          480.5,
          377.0
        ],
        [
          473.5,
          374.0
        ],
        [
          468.5,
          354.0
        ],
        [
          463.5,
          352.0
        ],
        [
          458.5,
          342.0
        ],
        [
          459.5,
          329.0
        ],
        [
          452.5,
          319.0
        ],
        [
          454.5,
          314.0
        ],
        [
          444.5,
          271.0
        ],
        [
          427.0,
          263.5
        ],
        [
          413.0,
          263.5
        ],
        [
          402.0,
          268.5
        ],
        [
          391.0,
          262.5
        ],
        [
          382.0,
          266.5
        ],
        [
          379.0,
          273.5
        ],
        [
          369.0,
          273.5
        ],
        [
          361.5,
          278.0
        ],
        [
          355.5,
          300.0
        ],
        [
          358.5,
          339.0
        ],
        [
          356.5,
          357.0
        ],
        [
          358.5,
          365.0
        ],
        [
          363.5,
          367.0
        ],
        [
          361.5,
          372.0
        ],
        [
          366.5,
          379.0
        ],
        [
          366.5,
          387.0
        ],
        [
          370.0,
          389.5
        ],
        [
          372.0,
          383.5
        ],
        [
          375.5,
          387.0
        ],
        [
          373.5,
          389.0
        ],
        [
          380.5,
          392.0
        ],
        [
          374.5,
          395.0
        ],
        [
          379.0,
          399.5
        ],
        [
          392.0,
          401.5
        ],
        [
          399.5,
          416.0
        ],
        [
          392.5,
          429.0
        ],
        [
          395.5,
          439.0
        ],
        [
          391.5,
          442.0
        ],
        [
          390.5,
          455.0
        ],
        [
          387.5,
          458.0
        ],
        [
          389.5,
          462.0
        ],
        [
          383.0,
          472.5
        ],
        [
          379.0,
          468.5
        ],
        [
          377.0,
          471.5
        ],
        [
          344.0,
          441.5
        ],
        [
          334.0,
          447.5
        ],
        [
          328.0,
          445.5
        ],
        [
          319.0,
          463.5
        ],
        [
          309.0,
          458.5
        ],
        [
          310.5,
          462.0
        ]
      ],
      "group_id": null,
      "description": "",
      "shape_type": "polygon",
      "flags": {},
      "mask": null
    }
  ],
  "imagePath": "d0699_jpg.rf.2503f5084a955a6267f596a94f354826.jpg",
  "imageData": null,
  "imageHeight": 640,
  "imageWidth": 640
}