{
  "version": "5.8.1",
  "flags": {},
  "shapes": [
    {
      "label": "DAMAGED_SIGN",
      "points": [
        [
          570.0,
          535.5
        ],
        [
          564.0,
          534.5
        ],
        [
          565.5,
          532.0
        ],
        [
          562.0,
          527.5
        ],
        [
          559.0,
          531.5
        ],
        [
          558.0,
          527.5
        ],
        [
          551.0,
          528.5
        ],
        [
          545.0,
          534.5
        ],
        [
          458.0,
          532.5
        ],
        [
          429.0,
          529.5
        ],
        [
          399.0,
          518.5
        ],
        [
          375.0,
          504.5
        ],
        [
          375.5,
          497.0
        ],
        [
          372.0,
          493.5
        ],
        [
          348.0,
          491.5
        ],
        [
          332.0,
          485.5
        ],
        [
          325.0,
          475.5
        ],
        [
          317.0,
          472.5
        ],
        [
          269.0,
          431.5
        ],
        [
          215.0,
          377.5
        ],
        [
          203.0,
          385.5
        ],
        [
          178.0,
          394.5
        ],
        [
          170.5,
          402.0
        ],
        [
          169.5,
          416.0
        ],
        [
          164.5,
          430.0
        ],
        [
          160.5,
          433.0
        ],
        [
          151.5,
          463.0
        ],
        [
          140.5,
          514.0
        ],
        [
          134.5,
          514.0
        ],
        [
          133.5,
          500.0
        ],
        [
          129.5,
          494.0
        ],
        [
          132.5,
          463.0
        ],
        [
          151.5,
          414.0
        ],
        [
          155.5,
          392.0
        ],
        [
          138.5,
          378.0
        ],
        [
          120.5,
          330.0
        ],
        [
          119.5,
          306.0
        ],
        [
          110.5,
          264.0
        ],
        [
          110.5,
          193.0
        ],
        [
          112.5,
          162.0
        ],
        [
          121.5,
          119.0
        ],
        [
          140.5,
          75.0
        ],
        [
          158.0,
          55.5
        ],
        [
          175.0,
          46.5
        ],
        [
          194.0,
          45.5
        ],
        [
          214.0,
          57.5
        ],
        [
          236.5,
          77.0
        ],
        [
          255.5,
          111.0
        ],
        [
          264.5,
          137.0
        ],
        [
          271.5,
          183.0
        ],
        [
          270.5,
          255.0
        ],
        [
          256.5,
          311.0
        ],
        [
          231.5,
          359.0
        ],
        [
          240.0,
          362.5
        ],
        [
          299.0,
          370.5
        ],
        [
          335.0,
          383.5
        ],
        [
          363.0,
          403.5
        ],
        [
          378.0,
          410.5
        ],
        [
          433.0,
          452.5
        ],
        [
          448.0,
          458.5
        ],
        [
          459.0,
          469.5
        ],
        [
          515.0,
          471.5
        ],
        [
          576.0,
          481.5
        ],
        [
          581.5,
          494.0
        ],
        [
          584.0,
          491.5
        ],
        [
          587.0,
          496.5
        ],
        [
          589.5,
          496.0
        ],
        [
          591.5,
          504.0
        ],
        [
          589.0,
          511.5
        ],
        [
          586.5,
          509.0
        ],
        [
          584.0,
          520.5
        ],
        [
          581.5,
          517.0
        ],
        [
          580.5,
          530.0
        ],
        [
          579.0,
          531.5
        ],
        [
          577.0,
          527.5
        ],
        [
          571.5,
          532.0
        ],
        [
          576.5,
          534.0
        ]
      ],
      "group_id": null,
      "description": "",
      "shape_type": "polygon",
      "flags": {},
      "mask": null
    }
  ],
  "imagePath": "d1103_jpg.rf.c00db50468f968db83494c17b73c5b22.jpg",
  "imageData": null,
  "imageHeight": 640,
  "imageWidth": 640
}