{
  "version": "5.8.1",
  "flags": {},
  "shapes": [
    {
      "label": "DAMAGED_SIGN",
      "points": [
        [
          289.0,
          616.5
        ],
        [
          277.0,
          614.5
        ],
        [
          281.5,
          612.0
        ],
        [
          274.0,
          609.5
        ],
        [
          226.0,
          604.5
        ],
        [
          167.0,
          580.5
        ],
        [
          122.0,
          550.5
        ],
        [
          81.5,
          512.0
        ],
        [
          50.5,
          463.0
        ],
        [
          31.5,
          420.0
        ],
        [
          23.5,
          390.0
        ],
        [
          19.5,
          359.0
        ],
        [
          24.5,
          302.0
        ],
        [
          19.5,
          284.0
        ],
        [
          21.5,
          261.0
        ],
        [
          46.5,
          191.0
        ],
        [
          73.5,
          149.0
        ],
        [
          113.0,
          106.5
        ],
        [
          153.0,
          75.5
        ],
        [
          200.0,
          51.5
        ],
        [
          212.0,
          50.5
        ],
        [
          221.0,
          43.5
        ],
        [
          244.0,
          38.5
        ],
        [
          247.0,
          41.5
        ],
        [
          250.0,
          37.5
        ],
        [
          271.0,
          31.5
        ],
        [
          375.0,
          31.5
        ],
        [
          426.0,
          43.5
        ],
        [
          470.0,
          61.5
        ],
        [
          476.5,
          67.0
        ],
        [
          474.0,
          88.5
        ],
        [
          483.0,
          87.5
        ],
        [
          489.0,
          79.5
        ],
        [
          509.0,
          86.5
        ],
        [
          544.5,
          117.0
        ],
        [
          579.5,
          157.0
        ],
        [
          609.5,
          210.0
        ],
        [
          624.5,
          256.0
        ],
        [
          632.5,
          311.0
        ],
        [
          629.5,
          367.0
        ],
        [
          614.5,
          425.0
        ],
        [
          589.5,
          477.0
        ],
        [
          549.5,
          526.0
        ],
        [
          505.0,
          564.5
        ],
        [
          460.0,
          589.5
        ],
        [
          449.0,
          591.5
        ],
        [
          449.0,
          594.5
        ],
        [
          430.0,
          600.5
        ],
        [
          414.0,
          599.5
        ],
        [
          407.5,
          602.0
        ],
        [
          413.0,
          604.5
        ],
        [
          397.0,
          605.5
        ],
        [
          395.0,
          609.5
        ],
        [
          389.0,
          605.5
        ],
        [
          348.0,
          611.5
        ],
        [
          351.5,
          614.0
        ],
        [
          349.0,
          615.5
        ],
        [
          316.0,
          612.5
        ]
      ],
      "group_id": null,
      "description": "",
      "shape_type": "polygon",
      "flags": {},
      "mask": null
    }
  ],
  "imagePath": "d1260_jpg.rf.cd14e08194ca9d67b7cff7eb808ef6da.jpg",
  "imageData": null,
  "imageHeight": 640,
  "imageWidth": 640
}