{
  "version": "5.8.1",
  "flags": {},
  "shapes": [
    {
      "label": "DAMAGED_SIGN",
      "points": [
        [
          334.0,
          542.5
        ],
        [
          323.5,
          541.0
        ],
        [
          324.0,
          538.5
        ],
        [
          326.0,
          541.5
        ],
        [
          330.5,
          540.0
        ],
        [
          330.5,
          532.0
        ],
        [
          337.5,
          527.0
        ],
        [
          333.5,
          524.0
        ],
        [
          340.5,
          524.0
        ],
        [
          339.0,
          518.5
        ],
        [
          335.0,
          520.5
        ],
        [
          332.5,
          518.0
        ],
        [
          332.0,
          513.5
        ],
        [
          330.0,
          517.5
        ],
        [
          322.0,
          512.5
        ],
        [
          318.0,
          515.5
        ],
        [
          312.0,
          513.5
        ],
        [
          310.0,
          517.5
        ],
        [
          297.0,
          517.5
        ],
        [
          293.0,
          521.5
        ],
        [
          282.0,
          521.5
        ],
        [
          260.5,
          513.0
        ],
        [
          256.5,
          495.0
        ],
        [
          254.5,
          452.0
        ],
        [
          261.5,
          412.0
        ],
        [
          278.5,
          379.0
        ],
        [
          289.5,
          372.0
        ],
        [
          287.5,
          369.0
        ],
        [
          297.0,
          363.5
        ],
        [
          309.0,
          365.5
        ],
        [
          310.5,
          362.0
        ],
        [
          304.0,
          357.5
        ],
        [
          301.0,
          359.5
        ],
        [
          302.0,
          356.5
        ],
        [
          297.0,
          357.5
        ],
        [
          290.0,
          348.5
        ],
        [
          287.0,
          351.5
        ],
        [
          282.0,
          345.5
        ],
        [
          242.0,
          335.5
        ],
        [
          211.0,
          309.5
        ],
        [
          197.5,
          290.0
        ],
        [
          176.5,
          274.0
        ],
        [
          164.5,
          249.0
        ],
        [
          156.5,
          215.0
        ],
        [
          156.5,
          164.0
        ],
        [
          160.5,
          159.0
        ],
        [
          166.5,
          132.0
        ],
        [
          188.5,
          95.0
        ],
        [
          208.0,
          73.5
        ],
        [
          232.0,
          55.5
        ],
        [
          262.0,
          42.5
        ],
        [
          295.0,
          35.5
        ],
        [
          329.0,
          35.5
        ],
        [
          334.0,
          39.5
        ],
        [
          343.0,
          38.5
        ],
        [
          348.0,
          42.5
        ],
        [
          365.0,
          44.5
        ],
        [
          377.0,
          52.5
        ],
        [
          387.0,
          52.5
        ],
        [
          391.0,
          57.5
        ],
        [
          397.0,
          57.5
        ],
        [
          399.0,
          62.5
        ],
        [
          402.0,
          60.5
        ],
        [
          409.0,
          69.5
        ],
        [
          412.0,
          68.5
        ],
        [
          418.5,
          75.0
        ],
        [
          417.5,
          82.0
        ],
        [
          427.5,
          89.0
        ],
        [
          419.0,
          90.5
        ],
        [
          419.0,
          93.5
        ],
        [
          450.0,
          99.5
        ],
        [
          457.5,
          108.0
        ],
        [
          473.5,
          143.0
        ],
        [
          478.5,
          173.0
        ],
        [
          478.5,
          205.0
        ],
        [
          474.5,
          231.0
        ],
        [
          471.5,
          243.0
        ],
        [
          453.5,
          279.0
        ],
        [
          421.0,
          314.5
        ],
        [
          412.0,
          320.5
        ],
        [
          401.5,
          315.0
        ],
        [
          400.5,
          319.0
        ],
        [
          409.0,
          320.5
        ],
        [
          410.5,
          324.0
        ],
        [
          407.5,
          335.0
        ],
        [
          404.0,
          336.5
        ],
        [
          401.5,
          334.0
        ],
        [
          403.5,
          341.0
        ],
        [
          407.0,
          337.5
        ],
        [
          407.5,
          342.0
        ],
        [
          402.0,
          342.5
        ],
        [
          399.0,
          339.5
        ],
        [
          394.0,
          345.5
        ],
        [
          389.0,
          341.5
        ],
        [
          390.5,
          349.0
        ],
        [
          383.0,
          349.5
        ],
        [
          379.5,
          360.0
        ],
        [
          375.5,
          362.0
        ],
        [
          386.5,
          375.0
        ],
        [
          384.0,
          376.5
        ],
        [
          378.0,
          369.5
        ],
        [
          374.0,
          375.5
        ],
        [
          369.0,
          368.5
        ],
        [
          364.0,
          368.5
        ],
        [
          359.5,
          373.0
        ],
        [
          360.5,
          378.0
        ],
        [
          350.5,
          382.0
        ],
        [
          358.5,
          387.0
        ],
        [
          356.5,
          392.0
        ],
        [
          358.5,
          400.0
        ],
        [
          362.5,
          402.0
        ],
        [
          358.5,
          403.0
        ],
        [
          360.5,
          407.0
        ],
        [
          363.5,
          407.0
        ],
        [
          364.0,
          402.5
        ],
        [
          369.5,
          411.0
        ],
        [
          375.5,
          414.0
        ],
        [
          375.0,
          419.5
        ],
        [
          366.5,
          422.0
        ],
        [
          370.5,
          424.0
        ],
        [
          375.5,
          435.0
        ],
        [
          380.5,
          436.0
        ],
        [
          378.5,
          442.0
        ],
        [
          382.5,
          449.0
        ],
        [
          374.5,
          452.0
        ],
        [
          382.5,
          470.0
        ],
        [
          371.0,
          470.5
        ],
        [
          370.0,
          457.5
        ],
        [
          362.0,
          460.5
        ],
        [
          360.5,
          466.0
        ],
        [
          368.5,
          469.0
        ],
        [
          364.0,
          469.5
        ],
        [
          359.5,
          474.0
        ],
        [
          360.5,
          478.0
        ],
        [
          353.0,
          481.5
        ],
        [
          350.5,
          487.0
        ],
        [
          362.0,
          487.5
        ],
        [
          364.0,
          484.5
        ],
        [
          367.0,
          486.5
        ],
        [
          371.5,
          482.0
        ],
        [
          371.0,
          476.5
        ],
        [
          381.0,
          476.5
        ],
        [
          388.5,
          489.0
        ],
        [
          381.0,
          491.5
        ],
        [
          378.5,
          488.0
        ],
        [
          378.5,
          491.0
        ],
        [
          385.5,
          495.0
        ],
        [
          379.0,
          497.5
        ],
        [
          377.0,
          495.5
        ],
        [
          376.5,
          502.0
        ],
        [
          387.0,
          500.5
        ],
        [
          389.5,
          508.0
        ],
        [
          386.0,
          510.5
        ],
        [
          384.0,
          507.5
        ],
        [
          377.0,
          519.5
        ],
        [
          371.0,
          513.5
        ],
        [
          367.0,
          528.5
        ],
        [
          362.0,
          524.5
        ],
        [
          359.0,
          527.5
        ],
        [
          357.0,
          524.5
        ],
        [
          352.0,
          528.5
        ],
        [
          348.0,
          527.5
        ]
      ],
      "group_id": null,
      "description": "",
      "shape_type": "polygon",
      "flags": {},
      "mask": null
    }
  ],
  "imagePath": "d1782_jpg.rf.519376ab0e07f7f32c19a988c82c972c.jpg",
  "imageData": null,
  "imageHeight": 640,
  "imageWidth": 640
}